witaker/__init__.py
witaker/clipboardserver/__init__.py
witaker/clipboardserver/__main__.py
witaker/clipboardserver/clipboard_model.py
witaker/clipboardserver/clipboard_server.py
witaker/clipboardserver/clipboard_server_main.py
witaker/clipboardserver/clipboard_server_run.py
witaker/clipboardserver/clipboard_util.py
witaker/clipboardserver/gui/__init__.py
witaker/clipboardserver/gui/__main__.py
witaker/clipboardserver/gui/clipboard_server_app.py
witaker/clipboardserver/gui/clipboard_server_main.py
witaker/clipboardserver/gui/icons/__init__.py
witaker/clipboardserver/gui/icons/copy-icon--active.png
witaker/clipboardserver/gui/icons/copy-icon--inactive.png
witaker/clipboardserver/gui/icons/copy-icon.svg
witaker/clipboardserver/gui/icons/settings--active.png
witaker/clipboardserver/gui/icons/settings--inactive.png
witaker/clipboardserver/gui/icons/settings-icon.svg
witaker/clipboardserver/gui/icons/witaker-clipboard-server.png
witaker/clipboardserver/gui/icons/witaker-clipboard-server.svg
witaker_clipboard_server-0.3.4.dist-info/LICENSE
witaker_clipboard_server-0.3.4.dist-info/METADATA
witaker_clipboard_server-0.3.4.dist-info/WHEEL
witaker_clipboard_server-0.3.4.dist-info/entry_points.txt
witaker_clipboard_server-0.3.4.dist-info/top_level.txt
witaker_clipboard_server-0.3.4.dist-info/RECORD
