Metadata-Version: 2.1
Name: witaker-clipboard-server
Version: 0.3.4
Summary: A utility for copy and paste in the browser without requiring focus
Home-page: https://github.com/cathalmcginley
Author: Cathal Mc Ginley
Author-email: cathal.pypi@gnostai.org
License: apache-2.0
Keywords: browser,copy,focus
Classifier: Development Status :: 5 - Production/Stable
Classifier: Intended Audience :: Developers
Classifier: License :: OSI Approved :: Apache Software License
Classifier: Programming Language :: Python :: 3
Classifier: Programming Language :: Python :: 3.6
Classifier: Programming Language :: Python :: 3.7
Classifier: Programming Language :: Python :: 3.8
Classifier: Programming Language :: Python :: 3.9
Requires-Python: >=3.6
License-File: LICENSE
Requires-Dist: Kivy (>=2.1.0)
Requires-Dist: xerox (>=0.4.1)
Requires-Dist: flask (>=2.0.3)
Requires-Dist: jsons (>=1.6.1)
Requires-Dist: flask-cors (>=3.0.10)
Requires-Dist: eventlet (>=0.33.0)
Requires-Dist: colorama (>=0.4.3)
